game_bot/__init__.py
game_bot/mouse_control.py
game_bot/picker.py
game_bot/picture.py
game_bot/window_control.py
game_bot-0.1.2.dist-info/LICENSE
game_bot-0.1.2.dist-info/METADATA
game_bot-0.1.2.dist-info/WHEEL
game_bot-0.1.2.dist-info/entry_points.txt
game_bot-0.1.2.dist-info/top_level.txt
game_bot-0.1.2.dist-info/RECORD
